[
  {"id":"60d0fe4f53112285291252a","name":"sara andersen","email":"sara.andersen@example.com","password":"123456"},
  {"id":"60d0fe4f5311236192j8e13a","name":"Ashish Kumar","email":"AshishKumar@example.com","password":"123456"},
  {"id":"60d0fe4f2512536168a109ca","name":"DhananjayNegi","email":"DhananjayNegi@example.com","password":"123456"},
  {"id":"60d0fe4f5355236168a109ca","name":"Vijay Rohila","email":"VijayRohila@example.com","password":"123456"},
  {"id":"60d0fe451251236168a109ca","name":"Vijay Rohila","email":"jamila@rumahweb.co.id","password":"Rumahweb123!@#"},
  [{"id":"test","name":"$name","email":"$password"}],[{"id":"test","name":"$name","email":"$password"}],
  [{"id":"test","name":"$name","email":"$password"}],[{"id":"asagasgas","name":null,"email":"1241521"}],
  [{"id":"asagasgas","name":null,"email":"asdasd","password":"124124"}]]